MANIFEST.in
README.rst
setup.py
docs/glossary.md
foowise.egg-info/PKG-INFO
foowise.egg-info/SOURCES.txt
foowise.egg-info/dependency_links.txt
foowise.egg-info/entry_points.txt
foowise.egg-info/not-zip-safe
foowise.egg-info/requires.txt
foowise.egg-info/top_level.txt
foowise/channels/Channel.py
foowise/channels/Cla.py
foowise/channels/DistSys.py
foowise/channels/Index.py
foowise/channels/InfoPair.py
foowise/channels/Infomorphism.py
foowise/channels/InfomorphismError.py
foowise/channels/Invariant.py
foowise/channels/JudgeSet.py
foowise/channels/Sequent.py
foowise/channels/Theory.py
foowise/channels/Value.py
foowise/channels/__init__.py
foowise/heuristic/GenQuotient.py
foowise/heuristic/__init__.py
foowise/math/Dual.py
foowise/math/LinAlg.py
foowise/math/Relation.py
foowise/math/Set.py
foowise/math/__init__.py