Metadata-Version: 1.1
Name: foowise
Version: 0.10
Summary: An implementation of Barwise-Seligman Channels
Home-page: https://github.com/ben-schulz/foowise
Author: Benjamin Schulz
Author-email: benjamin.john.schulz@gmail.com
License: MIT
Platform: UNKNOWN
Classifier: Development Status :: 2 - Pre-Alpha
Classifier: Intended Audience :: Science/Research
Classifier: Natural Language :: English
Classifier: Topic :: Scientific/Engineering
